pvpumpingsystem/__init__.py
pvpumpingsystem/consumption.py
pvpumpingsystem/errors.py
pvpumpingsystem/finance.py
pvpumpingsystem/function_models.py
pvpumpingsystem/inverse.py
pvpumpingsystem/mppt.py
pvpumpingsystem/pipenetwork.py
pvpumpingsystem/pump.py
pvpumpingsystem/pvgeneration.py
pvpumpingsystem/pvpumpsystem.py
pvpumpingsystem/reservoir.py
pvpumpingsystem/sizing.py
pvpumpingsystem/waterproperties.py
pvpumpingsystem-0.9.dist-info/LICENSE
pvpumpingsystem-0.9.dist-info/METADATA
pvpumpingsystem-0.9.dist-info/WHEEL
pvpumpingsystem-0.9.dist-info/top_level.txt
pvpumpingsystem-0.9.dist-info/RECORD
